qpymenu/__init__.py
qpymenu/__main__.py
qpymenu/ansi.py
qpymenu/qpymenu.py
qpymenu-0.6.2.dist-info/METADATA
qpymenu-0.6.2.dist-info/WHEEL
qpymenu-0.6.2.dist-info/top_level.txt
qpymenu-0.6.2.dist-info/RECORD
