Metadata-Version: 2.4
Name: qpymenu
Version: 0.6.2
Summary: A terminal-based ANSI-formatted menu system with nested menus, threading, logging, and user prompts.
Author: David J. Cartwright
Author-email: "David J. Cartwright" <davidcartwright@hotmail.com>
License: MIT
Project-URL: Homepage, https://github.com/cartwrightdj/qpymenu
Project-URL: Documentation, https://qpymenu.readthedocs.io/en/latest/index.html
Project-URL: Issues, https://github.com/cartwrightdj/qpymenu/issues
Keywords: cli,menu,terminal,ansi,threading,interactive,pymenu
Classifier: Development Status :: 4 - Beta
Classifier: Programming Language :: Python :: 3
Classifier: Environment :: Console
Classifier: License :: OSI Approved :: MIT License
Classifier: Operating System :: OS Independent
Classifier: Topic :: Utilities
Classifier: Topic :: Software Development :: User Interfaces
Requires-Python: >=3.6
Dynamic: author
Dynamic: requires-python
